mac_vendor_lookup.py
mac_vendor_lookup-0.1.12.data/data/cache/mac-vendors.txt
mac_vendor_lookup-0.1.12.dist-info/LICENCE
mac_vendor_lookup-0.1.12.dist-info/METADATA
mac_vendor_lookup-0.1.12.dist-info/WHEEL
mac_vendor_lookup-0.1.12.dist-info/entry_points.txt
mac_vendor_lookup-0.1.12.dist-info/top_level.txt
mac_vendor_lookup-0.1.12.dist-info/RECORD
