Metadata-Version: 2.1
Name: mac_vendor_lookup
Version: 0.1.12
Summary: Find the vendor for a given MAC address
Home-page: https://github.com/bauerj/mac_vendor_lookup
Author: Johann Bauer
Author-email: pypi.org@bauerj.eu
License: UNKNOWN
Keywords: mac-address OUI lookup
Platform: UNKNOWN
Classifier: Development Status :: 5 - Production/Stable
Classifier: Intended Audience :: Developers
Classifier: Topic :: Software Development :: Libraries
Classifier: Topic :: Software Development :: Libraries :: Python Modules
Classifier: Topic :: System :: Networking
Classifier: License :: OSI Approved :: Apache Software License
Classifier: Programming Language :: Python :: 3.5
Classifier: Programming Language :: Python :: 3.6
Classifier: Programming Language :: Python :: 3.7
Requires-Python: <4, >=3.5
Provides-Extra: test
License-File: LICENCE
